aws_sagemaker_remote/__init__.py
aws_sagemaker_remote/args.py
aws_sagemaker_remote/cli.py
aws_sagemaker_remote/commands.py
aws_sagemaker_remote/git.py
aws_sagemaker_remote/iam.py
aws_sagemaker_remote/md5.py
aws_sagemaker_remote/modules.py
aws_sagemaker_remote/mpworkers.py
aws_sagemaker_remote/s3.py
aws_sagemaker_remote/session.py
aws_sagemaker_remote/tags.py
aws_sagemaker_remote/batch/__init__.py
aws_sagemaker_remote/batch/job.py
aws_sagemaker_remote/batch/main.py
aws_sagemaker_remote/batch/report.py
aws_sagemaker_remote/ecr/__init__.py
aws_sagemaker_remote/ecr/buildspec.yml
aws_sagemaker_remote/ecr/command.py
aws_sagemaker_remote/ecr/image_build.yml
aws_sagemaker_remote/ecr/images.py
aws_sagemaker_remote/ecr/inference/latest/Dockerfile
aws_sagemaker_remote/ecr/inference/latest/config.properties
aws_sagemaker_remote/ecr/inference/latest/dockerd-entrypoint.py
aws_sagemaker_remote/ecr/inference/latest/requirements.txt
aws_sagemaker_remote/ecr/inference/py27-gpu-tf/Dockerfile
aws_sagemaker_remote/ecr/inference/py27-gpu-tf/config.properties
aws_sagemaker_remote/ecr/inference/py27-gpu-tf/dockerd-entrypoint.py
aws_sagemaker_remote/ecr/inference/py27-gpu-tf/requirements.txt
aws_sagemaker_remote/ecr/inference/py27-tf/Dockerfile
aws_sagemaker_remote/ecr/inference/py27-tf/config.properties
aws_sagemaker_remote/ecr/inference/py27-tf/dockerd-entrypoint.py
aws_sagemaker_remote/ecr/inference/py27-tf/requirements.txt
aws_sagemaker_remote/ecr/processing/latest/Dockerfile
aws_sagemaker_remote/ecr/processing/py27/Dockerfile
aws_sagemaker_remote/ecr/processing/py27-gpu-tf/Dockerfile
aws_sagemaker_remote/ecr/training/gpu/Dockerfile
aws_sagemaker_remote/ecr/training/gpu/start_container.sh
aws_sagemaker_remote/ecr/training/latest/Dockerfile
aws_sagemaker_remote/ecr/training/latest/start_container.sh
aws_sagemaker_remote/inference/__init__.py
aws_sagemaker_remote/inference/command.py
aws_sagemaker_remote/inference/endpoint.py
aws_sagemaker_remote/inference/endpoint_config.py
aws_sagemaker_remote-0.0.71.dist-info/METADATA
aws_sagemaker_remote-0.0.71.dist-info/WHEEL
aws_sagemaker_remote-0.0.71.dist-info/entry_points.txt
aws_sagemaker_remote-0.0.71.dist-info/top_level.txt
aws_sagemaker_remote-0.0.71.dist-info/RECORD
