Metadata-Version: 2.1
Name: aws-sagemaker-remote
Version: 0.0.71
Summary: Simplify running processing and training remotely on AWS SageMaker
Home-page: https://github.com/bstriner/aws-sagemaker-remote
Author: Ben Striner
Author-email: bstriner@gmail.com
License: UNKNOWN
Platform: UNKNOWN
Requires-Dist: sagemaker
Requires-Dist: sagemaker-experiments
Requires-Dist: click
